graphtk/__init__.py
graphtk/adjacency_list.py
graphtk/edges.py
graphtk/graph_coloring.py
graphtk/graph_init.py
graphtk/graphs.py
graphtk/matrix.py
graphtk/toolkit.py
graphtk-1.0.1.dist-info/licenses/LICENSE
graphtk-1.0.1.dist-info/METADATA
graphtk-1.0.1.dist-info/WHEEL
graphtk-1.0.1.dist-info/entry_points.txt
graphtk-1.0.1.dist-info/top_level.txt
graphtk-1.0.1.dist-info/RECORD
