Metadata-Version: 2.4
Name: graphtk
Version: 1.0.1
Summary: Graph Theory Toolkit (GraphTK)
Author-email: Ansh Soni <ansh.mn.soni7505@gmail.com>
Requires-Python: >=3.7
License-File: LICENSE
Dynamic: license-file
